MANIFEST.in
changelog.rst
readme.rst
setup.py
BlazeCommandHelper.egg-info/PKG-INFO
BlazeCommandHelper.egg-info/SOURCES.txt
BlazeCommandHelper.egg-info/dependency_links.txt
BlazeCommandHelper.egg-info/not-zip-safe
BlazeCommandHelper.egg-info/requires.txt
BlazeCommandHelper.egg-info/top_level.txt
blazech/__init__.py
blazech/application.py
blazech/baseparser.py
blazech/commands.py
blazech/config.py
blazech/exceptions.py
blazech/locations.py
blazech/log.py
blazech/actions/__init__.py
blazech/actions/databases.py
blazech/actions/reporting.py
blazech/lib/ConfigParser.py
blazech/lib/__init__.py
blazech/tests/__init__.py
blazech/tests/helpers.py
blazech/tests/test_cmdapp.py
blazech/tests/test_configs.py
blazech/tests/test_logging.py
blazech/tests/test_usage.py
blazech/tests/test_utils.py
blazech/tests/cmdapp/__init__.py
blazech/tests/cmdapp/commands.py
blazech/tests/cmdapp/entry_points.py
docs/ideas.txt
docs/index.txt
scripts/bch