Metadata-Version: 1.0
Name: BlazeCommandHelper
Version: 0.2.0
Summary: A framework that facilitates shell and batch scripting in Python
Home-page: http://bitbucket.org/rsyring/blazech/
Author: Randy Syring
Author-email: rsyring@gmail.com
License: BSD
Platform: UNKNOWN
Classifier: Development Status :: 4 - Beta
Classifier: Intended Audience :: Developers
Classifier: Intended Audience :: System Administrators
Classifier: License :: OSI Approved :: BSD License
